{"cameraMode":{"drawMode":0,"name":"Shaded","section":"Shading Mode"},"sceneLighting":true,"audioPlay":false,"sceneViewState":{"m_AlwaysRefresh":false,"showFog":true,"showSkybox":true,"showFlares":true,"showImageEffects":true,"showParticleSystems":true,"showVisualEffectGraphs":true,"m_FxEnabled":true},"in2DMode":false,"pivot":{"x":4.87644100189209,"y":1.8075315952301026,"z":15.19687557220459},"rotation":{"x":-0.02904527448117733,"y":-0.14825262129306794,"z":0.004542199894785881,"w":-0.9886892437934876},"size":6.328782558441162,"orthographic":false}